{
  "app": {
    "name": "SD Overseas",
    "description": "Premium Indische Gewürze Import & Export",
    "tagline": "Die Welt mit authentischen indischen Aromen verbinden"
  },
  "company": {
    "name": "SD Overseas",
    "description": "SD Overseas spezialisiert sich auf den Import und Export hochwertiger indischer Gewürze und verbindet Unternehmen weltweit mit den reichen Aromen Indiens.",
    "address": {
      "street": "123 Gewürzstraße",
      "city": "Mumbai",
      "state": "Maharashtra",
      "country": "Indien",
      "postalCode": "400001"
    },
    "contact": {
      "email": "info@sdoverseas.com",
      "phone": "+91 98765 43210",
      "whatsapp": "+91 98765 43210"
    },
    "social": {
      "linkedin": "https://linkedin.com/company/sd-overseas",
      "twitter": "https://twitter.com/sdoverseas",
      "facebook": "https://facebook.com/sdoverseas",
      "instagram": "https://instagram.com/sdoverseas"
    },
    "businessHours": {
      "weekdays": "9:00 - 18:00",
      "saturday": "9:00 - 16:00",
      "sunday": "Geschlossen"
    }
  },
  "navigation": {
    "items": [
      { "name": "Startseite", "href": "/" },
      { "name": "Über uns", "href": "/about" },
      { "name": "Produkte", "href": "/products" },
      { "name": "Dienstleistungen", "href": "/services" },
      { "name": "Kontakt", "href": "/contact" }
    ],
    "homeVariants": []
  },
  "theme": {
    "primary": "orange",
    "secondary": "blue",
    "accent": "green"
  },
  "themes": {
    "home": [
      {
        "name": "Startseite Final",
        "href": "/",
        "description": "Modernes, professionelles Design mit Hero-Bereich und empfohlenen Inhalten"
      }
    ]
  }
}
